[{"id":1,"fullname":"Nguyen Huy Tuong","gender":true,"age":18},{"id":2,"fullname":"Bùi Tuấn Anh","gender":false,"age":0},{"id":3,"fullname":"Bùi Tuấn Anh","gender":false,"age":0},{"id":4,"fullname":"ニアン","gender":false,"age":1},{"id":5,"fullname":"","gender":false,"age":1},{"id":6,"fullname":"Ȩ","gender":false,"age":1},{"id":7,"fullname":"a","gender":false,"age":1},{"id":8,"fullname":"a","gender":false,"age":1},{"id":9,"fullname":"Tuấn","gender":false,"age":1},{"id":10,"fullname":"abc","gender":false,"age":1},{"id":11,"fullname":"Ẻ","gender":false,"age":1}]